README.md
setup.py
GFETStimulation/GuiStim.py
GFETStimulation/StimCore.py
GFETStimulation/__init__.py
PyCharactStimulation.egg-info/PKG-INFO
PyCharactStimulation.egg-info/SOURCES.txt
PyCharactStimulation.egg-info/dependency_links.txt
PyCharactStimulation.egg-info/entry_points.txt
PyCharactStimulation.egg-info/requires.txt
PyCharactStimulation.egg-info/top_level.txt