Metadata-Version: 1.2
Name: PyCharactStimulation
Version: 0.0.1
Summary: Electrodes stimulation tools
Home-page: https://github.com/jmartinezaguilar/PyCharactStimulation
Author: Javier Martínez Aguilar
Author-email: Javier.Martinez@imb-cnm.csic.es
Maintainer: Javier Martinez-Aguilar
Maintainer-email: Javier.Martinez@imb-cnm.csic.es
License: GPLv3
Download-URL: https://github.com/jmartinezaguilar/PyCharactStimulation
Platform: UNKNOWN
Classifier: Development Status :: 3 - Alpha
Classifier: Environment :: Console
Classifier: Environment :: X11 Applications :: Qt
Classifier: Environment :: Win32 (MS Windows)
Classifier: Intended Audience :: Science/Research
Classifier: License :: OSI Approved :: GNU General Public License (GPL)
Classifier: Operating System :: Microsoft :: Windows
Classifier: Operating System :: POSIX
Classifier: Operating System :: POSIX :: Linux
Classifier: Operating System :: Unix
Classifier: Operating System :: OS Independent
Classifier: Programming Language :: Python
Classifier: Programming Language :: Python :: 2.7
Classifier: Topic :: Scientific/Engineering
Classifier: Topic :: Software Development :: User Interfaces
